bluesky/__init__.py
bluesky/__main__.py
bluesky/cmdargs.py
bluesky/pathfinder.py
bluesky/settings.py
bluesky/core/__init__.py
bluesky/core/entity.py
bluesky/core/plugin.py
bluesky/core/replaceable.py
bluesky/core/signal.py
bluesky/core/simtime.py
bluesky/core/trafficarrays.py
bluesky/core/varexplorer.py
bluesky/core/walltime.py
bluesky/navdatabase/__init__.py
bluesky/navdatabase/loadnavdata.py
bluesky/navdatabase/loadnavdata_txt.py
bluesky/navdatabase/navdatabase.py
bluesky/network/__init__.py
bluesky/network/client.py
bluesky/network/common.py
bluesky/network/detached.py
bluesky/network/discovery.py
bluesky/network/node.py
bluesky/network/node_mt.py
bluesky/network/npcodec.py
bluesky/network/server.py
bluesky/plugins/__init__.py
bluesky/plugins/adsb_decoder.py
bluesky/plugins/adsbfeed.py
bluesky/plugins/area.py
bluesky/plugins/example.py
bluesky/plugins/geofence.py
bluesky/plugins/geovector.py
bluesky/plugins/guiexample.py
bluesky/plugins/ilsgate.py
bluesky/plugins/importer_example.py
bluesky/plugins/metrics.py
bluesky/plugins/mlcontrol.py
bluesky/plugins/opensky.py
bluesky/plugins/sectorcount.py
bluesky/plugins/stackcheck.py
bluesky/plugins/synthetic.py
bluesky/plugins/trafgen.py
bluesky/plugins/trafgenclasses.py
bluesky/plugins/windecmwf.py
bluesky/plugins/windgfs.py
bluesky/plugins/asas/eby.py
bluesky/plugins/asas/ssd.py
bluesky/plugins/asas/swarm.py
bluesky/resources/default.cfg
bluesky/simulation/__init__.py
bluesky/simulation/screenio.py
bluesky/simulation/simulation.py
bluesky/stack/__init__.py
bluesky/stack/argparser.py
bluesky/stack/basecmds.py
bluesky/stack/clientstack.py
bluesky/stack/cmdparser.py
bluesky/stack/importer.py
bluesky/stack/recorder.py
bluesky/stack/simstack.py
bluesky/stack/stackbase.py
bluesky/test/__init__.py
bluesky/test/tcp/__init__.py
bluesky/test/tcp/conftest.py
bluesky/test/tcp/test_simple.py
bluesky/test/traffic/__init__.py
bluesky/test/traffic/conftest.py
bluesky/test/traffic/test_route_wpt.py
bluesky/test/traffic/test_traffic.py
bluesky_simulator-2024.7.1.dist-info/LICENSE
bluesky_simulator-2024.7.1.dist-info/METADATA
bluesky_simulator-2024.7.1.dist-info/WHEEL
bluesky_simulator-2024.7.1.dist-info/entry_points.txt
bluesky_simulator-2024.7.1.dist-info/top_level.txt
bluesky_simulator-2024.7.1.dist-info/RECORD
