Metadata-Version: 2.1
Name: bluesky-simulator
Version: 2024.7.1
Summary: The Open Air Traffic Simulator
Home-page: https://github.com/TUDelft-CNS-ATM/bluesky
Author: The BlueSky community
Maintainer: Jacco Hoekstra and Joost Ellerbroek
License: GNU General Public License v3 (GPLv3)
Project-URL: Source, https://github.com/TUDelft-CNS-ATM/bluesky
Keywords: atm transport simulation aviation aircraft
Classifier: Development Status :: 4 - Beta
Classifier: Intended Audience :: Science/Research
Classifier: Topic :: Scientific/Engineering
Classifier: License :: OSI Approved :: GNU General Public License v3 (GPLv3)
Classifier: Programming Language :: Python :: 3.7
Classifier: Programming Language :: Python :: 3.8
Classifier: Programming Language :: Python :: 3.9
Classifier: Programming Language :: Python :: 3.10
License-File: LICENSE
Requires-Dist: numpy
Requires-Dist: scipy
Requires-Dist: matplotlib
Requires-Dist: msgpack >=1.0.0
Requires-Dist: zmq
Requires-Dist: pandas
Requires-Dist: bluesky-simdata
Provides-Extra: console
Requires-Dist: textual ; extra == 'console'
Provides-Extra: dev
Requires-Dist: check-manifest ; extra == 'dev'
Provides-Extra: full
Requires-Dist: pygame ; extra == 'full'
Requires-Dist: pyopengl ; extra == 'full'
Requires-Dist: PyQt6 ; extra == 'full'
Requires-Dist: PyQt6-WebEngine ; extra == 'full'
Requires-Dist: textual ; extra == 'full'
Requires-Dist: bluesky-guidata ; extra == 'full'
Provides-Extra: headless
Provides-Extra: pygame
Requires-Dist: pygame ; extra == 'pygame'
Provides-Extra: qt5
Requires-Dist: pyopengl ; extra == 'qt5'
Requires-Dist: PyQt5 ; extra == 'qt5'
Requires-Dist: PyQtWebEngine-Qt5 ; extra == 'qt5'
Requires-Dist: bluesky-guidata ; extra == 'qt5'
Provides-Extra: qt6
Requires-Dist: pyopengl ; extra == 'qt6'
Requires-Dist: PyQt6 ; extra == 'qt6'
Requires-Dist: PyQt6-WebEngine ; extra == 'qt6'
Requires-Dist: bluesky-guidata ; extra == 'qt6'
Provides-Extra: test
Requires-Dist: coverage ; extra == 'test'
Requires-Dist: flake8 ; extra == 'test'
Requires-Dist: radon ; extra == 'test'
Requires-Dist: nose ; extra == 'test'
